LICENSE.txt
MANIFEST.in
README.md
requirements.txt
setup.cfg
setup.py
examples/wordcount.py
featureflow/__init__.py
featureflow/bytestream.py
featureflow/data.py
featureflow/database_iterator.py
featureflow/datawriter.py
featureflow/decoder.py
featureflow/dummyserver.py
featureflow/encoder.py
featureflow/eventlog.py
featureflow/extractor.py
featureflow/feature.py
featureflow/iteratornode.py
featureflow/lmdbstore.py
featureflow/model.py
featureflow/nmpy.py
featureflow/objectstore.py
featureflow/persistence.py
featureflow/test_bytestream.py
featureflow/test_data.py
featureflow/test_datawriter.py
featureflow/test_eventlog.py
featureflow/test_integration.py
featureflow/test_lmdbstore.py
featureflow/test_multiprocessing.py
featureflow/test_nmpy.py
featureflow/test_objectstorage.py
featureflow/test_persistence.py
featureflow/util.py
featureflow/var.py
featureflow.egg-info/PKG-INFO
featureflow.egg-info/SOURCES.txt
featureflow.egg-info/dependency_links.txt
featureflow.egg-info/requires.txt
featureflow.egg-info/top_level.txt