Metadata-Version: 1.1
Name: featureflow
Version: 2.12.1
Summary: UNKNOWN
Home-page: https://github.com/JohnVinyard/featureflow
Author: John Vinyard
Author-email: john.vinyard@gmail.com
License: UNKNOWN
Download-URL: https://github.com/jvinyard/featureflow/tarball/2.12.1
Platform: UNKNOWN
